fw_gear_dcm2niix/__init__.py
fw_gear_dcm2niix/dcm2niix/__init__.py
fw_gear_dcm2niix/dcm2niix/arrange.py
fw_gear_dcm2niix/dcm2niix/dcm2niix_run.py
fw_gear_dcm2niix/dcm2niix/dcm2niix_utils.py
fw_gear_dcm2niix/dcm2niix/interfaces.py
fw_gear_dcm2niix/dcm2niix/prepare.py
fw_gear_dcm2niix/utils/__init__.py
fw_gear_dcm2niix/utils/metadata.py
fw_gear_dcm2niix/utils/parse_config.py
fw_gear_dcm2niix/utils/resolve.py
fw_gear_dcm2niix-2.1.9.dist-info/METADATA
fw_gear_dcm2niix-2.1.9.dist-info/WHEEL
fw_gear_dcm2niix-2.1.9.dist-info/licenses/LICENSE
fw_gear_dcm2niix-2.1.9.dist-info/RECORD
