Metadata-Version: 2.4
Name: fw-gear-dcm2niix
Version: 2.1.9
Summary: A Flywheel Gear for implementing Chris Rorden's dcm2niix for converting DICOM (or PAR/REC) to NIfTI (or NRRD).
Project-URL: Repository, https://gitlab.com/flywheel-io/scientific-solutions/gears/dcm2niix/
Author-email: Flywheel <support@flywheel.io>
License-File: LICENSE
Keywords: Flywheel,Gears
Classifier: Topic :: Scientific/Engineering
Requires-Python: ~=3.12
Requires-Dist: fw-gear-file-metadata-importer>=1.5.9
Requires-Dist: nipype~=1.8.4
